boundary_layer/__init__.py
boundary_layer/_version.py
boundary_layer/containers.py
boundary_layer/exceptions.py
boundary_layer/graph.py
boundary_layer/logger.py
boundary_layer/pretty_yaml.py
boundary_layer/util.py
boundary_layer/validator.py
boundary_layer/workflow.py
boundary_layer/builders/__init__.py
boundary_layer/builders/base.py
boundary_layer/builders/generator.py
boundary_layer/builders/primary.py
boundary_layer/builders/subdag.py
boundary_layer/builders/util.py
boundary_layer/builders/templates/generator_epilogue.j2
boundary_layer/builders/templates/generator_operator.j2
boundary_layer/builders/templates/generator_preamble.j2
boundary_layer/builders/templates/operator.j2
boundary_layer/builders/templates/primary_preamble.j2
boundary_layer/builders/templates/subdag_epilogue.j2
boundary_layer/builders/templates/subdag_operator.j2
boundary_layer/builders/templates/subdag_preamble.j2
boundary_layer/oozier/__init__.py
boundary_layer/oozier/actions.py
boundary_layer/oozier/cluster_config.py
boundary_layer/oozier/file_fetcher.py
boundary_layer/oozier/jsp_macros.py
boundary_layer/oozier/parse.py
boundary_layer/oozier/schema.py
boundary_layer/plugins/__init__.py
boundary_layer/plugins/base.py
boundary_layer/plugins/oozie_plugin.py
boundary_layer/plugins/plugin_manager.py
boundary_layer/plugins/util.py
boundary_layer/registry/__init__.py
boundary_layer/registry/registry.py
boundary_layer/registry/types/__init__.py
boundary_layer/registry/types/generator.py
boundary_layer/registry/types/operator.py
boundary_layer/registry/types/preprocessor.py
boundary_layer/registry/types/resource.py
boundary_layer/registry/types/subdag.py
boundary_layer/schemas/__init__.py
boundary_layer/schemas/base.py
boundary_layer/schemas/dag.py
boundary_layer/schemas/internal/__init__.py
boundary_layer/schemas/internal/base.py
boundary_layer/schemas/internal/generators.py
boundary_layer/schemas/internal/operators.py
boundary_layer/schemas/internal/resources.py
boundary_layer-1.9.18.dist-info/LICENSE
boundary_layer-1.9.18.dist-info/METADATA
boundary_layer-1.9.18.dist-info/NOTICE
boundary_layer-1.9.18.dist-info/WHEEL
boundary_layer-1.9.18.dist-info/entry_points.txt
boundary_layer-1.9.18.dist-info/top_level.txt
boundary_layer-1.9.18.dist-info/RECORD
