Metadata-Version: 2.1
Name: boundary-layer
Version: 1.9.18
Summary: Builds Airflow DAGs from configuration files
Home-page: https://github.com/etsy/boundary-layer
Author: Kevin McHale
Author-email: kmchale@etsy.com
License: Apache License 2.0
Keywords: airflow
Classifier: Development Status :: 5 - Production/Stable
Classifier: Environment :: Console
Classifier: Intended Audience :: Developers
Classifier: License :: OSI Approved :: Apache Software License
Classifier: Operating System :: OS Independent
Classifier: Programming Language :: Python :: 3.6
Classifier: Programming Language :: Python :: 3.7
Classifier: Programming Language :: Python :: 3.8
Classifier: Programming Language :: Python :: 3.9
Classifier: Topic :: Utilities
Requires-Python: >=3.6
License-File: LICENSE
License-File: NOTICE
Requires-Dist: semver (<3.0,>=2.7.0)
Requires-Dist: jsonschema (<3.0,>=2.6.0)
Requires-Dist: jinja2 (>=2.8.1)
Requires-Dist: pyyaml (>=4.2b1)
Requires-Dist: marshmallow (<3.0,>=2.13.6)
Requires-Dist: networkx (<2.5,>=2.4)
Requires-Dist: xmltodict (<1.0,>=0.11.0)
Requires-Dist: six (<2.0,>=1.11.0)
Requires-Dist: markupsafe (==2.0.1)
Requires-Dist: importlib-metadata (<5.0)
Provides-Extra: github
Requires-Dist: github3.py (>=1.1) ; extra == 'github'
